{"listdata":
[{"path": "truco/res/GUI/", "name": "truco_0.png", "md5": "7b2dc58a994f12e32c05626693e411f2","size":1539},
{"path": "truco/res/GUI/", "name": "truco_1.png", "md5": "ee0515116f1682363ce1b30d78f90b3a","size":1404},
{"path": "truco/res/GUI/", "name": "truco_12.png", "md5": "e5c8e59dc0f0d1b51652ccb577f0ec1b","size":1733},
{"path": "truco/res/GUI/", "name": "truco_3.png", "md5": "7df2d4ad65e4af6833cd057d6a3102b7","size":1652},
{"path": "truco/res/GUI/", "name": "truco_6.png", "md5": "2581fef983b4db2e73dbdc7e500c6aba","size":1630},
{"path": "truco/res/GUI/", "name": "truco_9.png", "md5": "293b8653ff596ced6f0dd678a2d54e2c","size":1585},
{"path": "truco/res/GUI/", "name": "truco_accept.png", "md5": "ac3a811236287bb38b4f2148038ad1cb","size":3411},
{"path": "truco/res/GUI/", "name": "truco_aumentar12.png", "md5": "6ee7b5eab2da580d8b4804ddbd87404d","size":3160},
{"path": "truco/res/GUI/", "name": "truco_aumentar6.png", "md5": "17ce9c59e73d362e92c3903b4dedd10a","size":3064},
{"path": "truco/res/GUI/", "name": "truco_aumentar9.png", "md5": "680ab7127ad1c0881b1dbde9bed9913b","size":3086},
{"path": "truco/res/GUI/", "name": "truco_bj.png", "md5": "6775bc4e114c71850ce2585fc17a66b8","size":890091},
{"path": "truco/res/GUI/", "name": "truco_btn_tag_1.png", "md5": "a2042594d7062ee18ce46d49c9c7a2a8","size":2270},
{"path": "truco/res/GUI/", "name": "truco_btn_tag_2.png", "md5": "b97a5695980da70fe40262a6e576e58d","size":2335},
{"path": "truco/res/GUI/", "name": "truco_btn_tag_3.png", "md5": "93682a5d50a2e2ad392478968c503aee","size":2911},
{"path": "truco/res/GUI/", "name": "truco_bubble_accept.png", "md5": "63b2d8b935e5c9404f0f789db529c068","size":3612},
{"path": "truco/res/GUI/", "name": "truco_bubble_au_12.png", "md5": "49dc0eccd57fb13fd812a885aeb946c4","size":6534},
{"path": "truco/res/GUI/", "name": "truco_bubble_au_6.png", "md5": "eec87a343b73424dc32a0f737b84f562","size":6221},
{"path": "truco/res/GUI/", "name": "truco_bubble_au_9.png", "md5": "352316a3fb39617d19856af86eb3c9b6","size":6072},
{"path": "truco/res/GUI/", "name": "truco_bubble_giveup.png", "md5": "03c3826da6f672133db4584cbcf2ae6d","size":3256},
{"path": "truco/res/GUI/", "name": "truco_bubble_truco_12.png", "md5": "4f5fd97dad75ed5b444e5e680e15f511","size":4349},
{"path": "truco/res/GUI/", "name": "truco_bubble_truco_3.png", "md5": "4d235d185819964ff1132e48edbeda29","size":3411},
{"path": "truco/res/GUI/", "name": "truco_bubble_truco_6.png", "md5": "29b0fb2f03cd2c8bf2b9582be4786b6a","size":4245},
{"path": "truco/res/GUI/", "name": "truco_bubble_truco_9.png", "md5": "65430147ee4bedcc3bc4991c3317db68","size":4118},
{"path": "truco/res/GUI/", "name": "truco_coinAdd.fnt", "md5": "62b2421a05120cca32c8b7400816af7d","size":2104},
{"path": "truco/res/GUI/", "name": "truco_coinAdd.png", "md5": "ffc629d03a560275089f0e43141db6f5","size":4049},
{"path": "truco/res/GUI/", "name": "truco_ddwj.png", "md5": "6e52edc4b8da8a1ab1e2fa1487da498e","size":6342},
{"path": "truco/res/GUI/", "name": "truco_ddwj_guang.png", "md5": "fa5805bde3906948a6b189c90e5da5be","size":3112},
{"path": "truco/res/GUI/", "name": "truco_djs.png", "md5": "5c66beb9dda7b1523d5c984244968973","size":6162},
{"path": "truco/res/GUI/", "name": "truco_djs_gd.png", "md5": "8d4cbb35bc7cc01cd8c7834d1e66d39f","size":1593},
{"path": "truco/res/GUI/", "name": "truco_flipcard.png", "md5": "b7c7824eeeeaf1894130abce801a9745","size":2034},
{"path": "truco/res/GUI/", "name": "truco_fsp.png", "md5": "5b216d6afd0ecc2f3c50b7c552c3411f","size":17645},
{"path": "truco/res/GUI/", "name": "truco_fsp_1.png", "md5": "3163afee0df9cc0c16880c8ae1dd2715","size":1362},
{"path": "truco/res/GUI/", "name": "truco_fsp_2.png", "md5": "0abfcb44a8d35b482dd4bd1e8981637f","size":1367},
{"path": "truco/res/GUI/", "name": "truco_fsp_3.png", "md5": "cc71a515b63ced5a90a41fb5b46cd553","size":1378},
{"path": "truco/res/GUI/", "name": "truco_fsp_fg.png", "md5": "5703c03d5d8b58a760cd47ade5ffc179","size":1711},
{"path": "truco/res/GUI/", "name": "truco_fsp_hong2.png", "md5": "cf7f1eabf66198f8e104dd43a1627ccf","size":5908},
{"path": "truco/res/GUI/", "name": "truco_fsp_lan2.png", "md5": "d612d9193e64a1f4a1415807285405bc","size":5784},
{"path": "truco/res/GUI/", "name": "truco_gd.png", "md5": "88761ec9e2785453447214f5a65b85bd","size":4768},
{"path": "truco/res/GUI/", "name": "truco_gddk.png", "md5": "197a193697786ff2568a1faf9f5b9b1a","size":13988},
{"path": "truco/res/GUI/", "name": "truco_giveup.png", "md5": "9811c73630023eed3086905b9a9ecb2e","size":3760},
{"path": "truco/res/GUI/", "name": "truco_gz.png", "md5": "cf678dcf6e6582fc17bd0c071bbac76f","size":3895},
{"path": "truco/res/GUI/", "name": "truco_head_bg_1.png", "md5": "813be92ec73383bf91553f9917a42bc4","size":2553},
{"path": "truco/res/GUI/", "name": "truco_head_bg_2.png", "md5": "ebb6f182beee6b9d076563e8d3d05de9","size":3702},
{"path": "truco/res/GUI/", "name": "truco_head_bg_down_1.png", "md5": "448de1d1f6a908e6de8f670a4c5903a5","size":4553},
{"path": "truco/res/GUI/", "name": "truco_head_bg_down_2.png", "md5": "b7af9569aa31f84189c16a9e93e4fc00","size":3943},
{"path": "truco/res/GUI/", "name": "truco_head_broad_1.png", "md5": "1070f94c4f2607c29a558622b6fd0512","size":2990},
{"path": "truco/res/GUI/", "name": "truco_head_broad_2.png", "md5": "3831bec2d00ec214968947761355c09b","size":3326},
{"path": "truco/res/GUI/", "name": "truco_head_clip.png", "md5": "6c2539318a7ca18fbaf7173782d371c8","size":2492},
{"path": "truco/res/GUI/", "name": "truco_head_noplayer.png", "md5": "e1bdc41a5fbc69a1291cdb2eb1a5b740","size":1603},
{"path": "truco/res/GUI/", "name": "truco_hz.png", "md5": "a3b82eaec39f0274781e769da7ca09b2","size":3540},
{"path": "truco/res/GUI/", "name": "truco_jinbi.png", "md5": "4b00eb5fe7f50855ea019fbd0bcdc907","size":2524},
{"path": "truco/res/GUI/", "name": "truco_jl.png", "md5": "155db91d8a4445da2a0327db636fd1e6","size":5669},
{"path": "truco/res/GUI/", "name": "truco_js_tcfj.png", "md5": "22ad84415619eb3fa33481df07501a48","size":5663},
{"path": "truco/res/GUI/", "name": "truco_lt.png", "md5": "f44d3db61bea5ea1a7052b8c858b110b","size":5522},
{"path": "truco/res/GUI/", "name": "truco_pe.png", "md5": "ed75e3ea7dcb3a0da596f29521b6137a","size":2855},
{"path": "truco/res/GUI/", "name": "truco_player_coin.png", "md5": "b89ee8465fa4b376afe691028efbc1a9","size":3162},
{"path": "truco/res/GUI/", "name": "truco_Pontos.png", "md5": "922148503fcb3da8c9b9577dad9ec31f","size":2435},
{"path": "truco/res/GUI/", "name": "truco_sc.png", "md5": "b289b55f3c2fbea2d4ac68746b989cbc","size":5165},
{"path": "truco/res/GUI/", "name": "truco_scoreBg.png", "md5": "32899491629a385db4a87491190c9fff","size":3099},
{"path": "truco/res/GUI/", "name": "truco_showcard.png", "md5": "65ea7a7ce08c41903ba5d89d27e5f839","size":3488},
{"path": "truco/res/GUI/", "name": "truco_tc.png", "md5": "c58d5a0385b502af3ecb86212d928eaf","size":2823},
{"path": "truco/res/GUI/", "name": "truco_tg_jqr.png", "md5": "180d8dff67a7d7f8129caad632ca5848","size":7434},
{"path": "truco/res/GUI/", "name": "truco_tg_tip.png", "md5": "e1b2eaea67b676e5426d72311b0d1aca","size":3006},
{"path": "truco/res/GUI/", "name": "truco_tg_zz.png", "md5": "f5f8bc100002dd1b691139412b48d96f","size":1464},
{"path": "truco/res/GUI/", "name": "truco_truco_12.png", "md5": "bb04518ea4c5a9b4e045203a5bf850b7","size":4253},
{"path": "truco/res/GUI/", "name": "truco_truco_3.png", "md5": "7471767e227ef8b84fdfa6ef9ac94a77","size":3614},
{"path": "truco/res/GUI/", "name": "truco_truco_6.png", "md5": "d829aa463be616a0e998ca2f5c3cb9b0","size":4106},
{"path": "truco/res/GUI/", "name": "truco_truco_9.png", "md5": "85032d8c612ed6596928b071a3767df5","size":4205},
{"path": "truco/res/GUI/", "name": "truco_txz_left.png", "md5": "cf9747ead89c66146113f94951ba0e9d","size":3152},
{"path": "truco/res/GUI/", "name": "truco_txz_right.png", "md5": "21cc40a7f43358bd0f40f8d304213039","size":3150},
{"path": "truco/res/GUI/", "name": "truco_txz_top.png", "md5": "b9489737ec208e16a958e234934330ab","size":3082},
{"path": "truco/res/GUI/", "name": "truco_waitTipBg.png", "md5": "0debc42b6b96182718673da6a555e35d","size":15086},
{"path": "truco/res/GUI/", "name": "truco_xxbt.png", "md5": "d25072bc9f73e865c2db1c4e060c0760","size":1479},
{"path": "truco/res/GUI/", "name": "truco_xxjt.png", "md5": "4594f504ef572632650f1d050103a441","size":1628},
{"path": "truco/res/GUI/", "name": "truco_xxsz.png", "md5": "7066fcf031fb8a1d87d472fa408e6852","size":3085},
{"path": "truco/res/GUI/", "name": "truco_ylp.png", "md5": "5417e344e034193ad382f72f892de648","size":9669},
{"path": "truco/res/GUI/", "name": "truco_yxg.png", "md5": "f78e3c25303083621d9fe83eeff8b5ca","size":2924},
{"path": "truco/res/GUI/", "name": "truco_yxk.png", "md5": "b5c88e9501cbd1e5e0af2907383de959","size":3390},
{"path": "truco/res/GUI/animation/", "name": "baoguang_1.png", "md5": "3d7e7a259f9e3dd33dc2ce75c010e6ed","size":38183},
{"path": "truco/res/GUI/animation/", "name": "baoguang_2.png", "md5": "3adf3510ef3a2adcaad06a7039795e69","size":28655},
{"path": "truco/res/GUI/animation/", "name": "baoguang_3.png", "md5": "9970add46f7d2eab5cf72556e91d67c4","size":31867},
{"path": "truco/res/GUI/animation/", "name": "baoguang_4.png", "md5": "02e58a64f7bfa8dbff6595f5d4289eb3","size":36107},
{"path": "truco/res/GUI/animation/", "name": "baoguang_5.png", "md5": "c51f6f0cba6c8f5485e86058aa990032","size":38675},
{"path": "truco/res/GUI/animation/", "name": "baoguang_6.png", "md5": "1152e0ebb1e0d77970d70e1d2e5d96ba","size":39313},
{"path": "truco/res/GUI/animation/", "name": "baoguang_7.png", "md5": "aeb75c66c54b820e62d5d200647c54eb","size":33843},
{"path": "truco/res/GUI/animation/", "name": "baoguang_8.png", "md5": "64b703850603320cbb29d7df9ce0c9a7","size":13768},
{"path": "truco/res/GUI/animation/", "name": "baoguang_9.png", "md5": "303338e23db7afccfebaaca19ee7983d","size":6462},
{"path": "truco/res/GUI/animation/", "name": "shanguang_1.png", "md5": "d8c6fe57dcb97108b76d7bdf5fdfe27b","size":34548},
{"path": "truco/res/GUI/animation/", "name": "shanguang_2.png", "md5": "1bba874e6de523b2e7ad1b3139e1fc64","size":37427},
{"path": "truco/res/GUI/animation/", "name": "shanguang_3.png", "md5": "83e55cea52a49475d82b9df7d7c3b052","size":33214},
{"path": "truco/res/GUI/animation/", "name": "shanguang_4.png", "md5": "90a985c0250632c2168b92e37f700fb5","size":5812},
{"path": "truco/res/GUI/animation/", "name": "sz.png", "md5": "3a2fd9c20631b745338459e7428f3991","size":10151},
{"path": "truco/res/GUI/animation/", "name": "truco_bubble_point.png", "md5": "604c00b3d2b903399999e0cbcc131063","size":1344},
{"path": "truco/res/GUI/animation/", "name": "truco_jiesuandonghua_shengli1_bg.png", "md5": "7441a77b73622ee94f973c0595a2fede","size":79507},
{"path": "truco/res/GUI/animation/", "name": "truco_jiesuandonghua_shengli2_bg.png", "md5": "f46fb3544cfbf03c03d298e3f3a4d58c","size":124813},
{"path": "truco/res/GUI/animation/", "name": "truco_jiesuandonghua_shengli3_bg.png", "md5": "4d3cf880b995b3fc73ebc31424020221","size":11006},
{"path": "truco/res/GUI/animation/", "name": "truco_jiesuandonghua_shengli4_bg.png", "md5": "f440591d1702d37f8a131ddec8c0337e","size":8259},
{"path": "truco/res/GUI/animation/", "name": "truco_jiesuandonghua_shengli5_bg.png", "md5": "ea8f4626b225acf79bb0a0fb66fe71a4","size":7815},
{"path": "truco/res/GUI/animation/", "name": "truco_jiesuandonghua_shengli6_bg.png", "md5": "3c4407af62e5e3f05689f1a3b6061425","size":18354},
{"path": "truco/res/GUI/animation/", "name": "truco_jiesuandonghua_shengli7_bg.png", "md5": "eea8b49ca7fa6eb2fcd204f38967e648","size":16991},
{"path": "truco/res/GUI/animation/", "name": "truco_jiesuandonghua_shibai1_bg.png", "md5": "b39ef3488ec221485364b508494eb17d","size":69106},
{"path": "truco/res/GUI/animation/", "name": "truco_jiesuandonghua_shibai2_bg.png", "md5": "cdbeb79d777dcf5417360d285cb169a1","size":123671},
{"path": "truco/res/GUI/animation/", "name": "truco_jiesuandonghua_shibai3_bg.png", "md5": "5ba8dc6dcf109bac8a1b8f4c7c5680c6","size":13686},
{"path": "truco/res/GUI/animation/", "name": "truco_jiesuandonghua_shibai4_bg.png", "md5": "579433eba47fdf14cad3d104283f1d45","size":8322},
{"path": "truco/res/GUI/animation/", "name": "truco_jiesuandonghua_shibai5_bg.png", "md5": "6330568d5de1b5e4ea086c4a3806c25c","size":7003},
{"path": "truco/res/GUI/animation/", "name": "truco_jiesuandonghua_shibai6_bg.png", "md5": "55c75d7f889866e2b642ba0e7c2fb4e3","size":11868},
{"path": "truco/res/GUI/animation/", "name": "truco_jiesuandonghua_shibai7_bg.png", "md5": "3861b19a1858f5645cfc1ba4774b06d8","size":8107},
{"path": "truco/res/GUI/animation/", "name": "truco_jiesuandonghua_shibai8_bg.png", "md5": "4d17dc8a13fcd0e6357a3eedfd9e5c30","size":15934},
{"path": "truco/res/GUI/animation/", "name": "truco_js_hz.png", "md5": "183d9907d22bb25137c5f09558107c21","size":3148},
{"path": "truco/res/GUI/animation/", "name": "truco_js_jxw.png", "md5": "38dd60457a210c152969e0e158d475cd","size":2893},
{"path": "truco/res/GUI/animation/", "name": "truco_js_pc.png", "md5": "28cd1f853251c9d7fad489a011e664f6","size":3560},
{"path": "truco/res/GUI/animation/", "name": "truco_js_tcfj.png", "md5": "22ad84415619eb3fa33481df07501a48","size":5663},
{"path": "truco/res/GUI/animation/", "name": "truco_result_dk.png", "md5": "20dff5e4d7ccc8c11a3b411a0ba0ced8","size":2891},
{"path": "truco/res/GUI/animation/", "name": "truco_xx1.png", "md5": "63fcc3c1136466bd1c3ada31e5f79ae3","size":2992},
{"path": "truco/res/GUI/animation/", "name": "truco_xxsz.png", "md5": "7066fcf031fb8a1d87d472fa408e6852","size":3085},
{"path": "truco/res/GUI/animation/", "name": "VSdonghua_0000_tx1.png", "md5": "271f2707b908475bccbdce65bbd1754c","size":18976},
{"path": "truco/res/GUI/animation/", "name": "VSdonghua_0001_tx2.png", "md5": "07411c39f576ad433f5c4355ebd8de60","size":18976},
{"path": "truco/res/GUI/animation/", "name": "VSdonghua_0002_tx3.png", "md5": "69bec34d2dd67158e453b5828a744870","size":18491},
{"path": "truco/res/GUI/animation/", "name": "VSdonghua_0003_tx4.png", "md5": "6318582dea6b07c1e2b060f36603962d","size":18491},
{"path": "truco/res/GUI/animation/", "name": "VSdonghua_0004_lz1.png", "md5": "d539cc4b7848b0eca9860388ce219d2c","size":1242},
{"path": "truco/res/GUI/animation/", "name": "VSdonghua_0005_lz2.png", "md5": "5af4b7c91be0a01c7cf37caf1a22d723","size":1284},
{"path": "truco/res/GUI/animation/", "name": "VSdonghua_0006_lz3.png", "md5": "b228041c44a78be4077d1c49d551fa86","size":1324},
{"path": "truco/res/GUI/animation/", "name": "VSdonghua_0007_lz4.png", "md5": "fd78d4e721fb5f73ac23c46e4c03dd23","size":1220},
{"path": "truco/res/GUI/animation/", "name": "VSdonghua_0008_lz5.png", "md5": "213d4b5ffaff54edf206efeb567239eb","size":1268},
{"path": "truco/res/GUI/animation/", "name": "VSdonghua_0009_lz6.png", "md5": "e61c2563b00a1ae000ba1a7cce4dcef5","size":1268},
{"path": "truco/res/GUI/animation/", "name": "VSdonghua_0010_lz7.png", "md5": "7f5ba7a31747d737f29a4d5e66389417","size":1366},
{"path": "truco/res/GUI/animation/", "name": "VSdonghua_0011_vs.png", "md5": "9da4318afedfb51158c33efb9b41466a","size":17375},
{"path": "truco/res/GUI/animation/", "name": "VSdonghua_0012_blue.png", "md5": "af4b4a45a550a355d6356fa494ee9173","size":76477},
{"path": "truco/res/GUI/animation/", "name": "VSdonghua_0013_red.png", "md5": "df1b2ff8042529fbc342dad2bc7b73db","size":85301},
{"path": "truco/res/GUI/animation/", "name": "VSdonghua_0014_gq3.png", "md5": "92aec60caac67725d181f35635d092c3","size":32518},
{"path": "truco/res/GUI/animation/", "name": "VSdonghua_0015_sd.png", "md5": "decc83c8726cadf84c83ce1b25c6cb33","size":14392},
{"path": "truco/res/GUI/animation/", "name": "VSdonghua_0016_gq2.png", "md5": "ba941b2466c0443fdf49440792f560a8","size":21707},
{"path": "truco/res/GUI/animation/", "name": "VSdonghua_0017_gq1.png", "md5": "df5ba0f05bcd1d862bf85faa493a9852","size":12947},
{"path": "truco/res/GUI/animation/", "name": "VSdonghua_0018_db.png", "md5": "1f9e4968810578fe7b139b53faa0c052","size":130804},
{"path": "truco/res/GUI/animation/", "name": "VSdonghua_bg.png", "md5": "d7241427246cb9f53066c314d2e5bdc1","size":83},
{"path": "truco/res/GUI/animation/", "name": "wenziguang1.png", "md5": "a253ef76002e7ce85e7232d374fda762","size":5183},
{"path": "truco/res/GUI/animation/", "name": "wenziguang10.png", "md5": "098e259acde883fc243b7f3d3fa9dc79","size":6496},
{"path": "truco/res/GUI/animation/", "name": "wenziguang11.png", "md5": "1cc17ee9d8d94adba1e6057ba944311a","size":3877},
{"path": "truco/res/GUI/animation/", "name": "wenziguang12.png", "md5": "a4321535e243b97c87963b0eca160146","size":1379},
{"path": "truco/res/GUI/animation/", "name": "wenziguang2.png", "md5": "9bb0865665e3ce22b801f3fa65ac9750","size":9147},
{"path": "truco/res/GUI/animation/", "name": "wenziguang3.png", "md5": "0ad85399581925c289c02cb8823cd811","size":11048},
{"path": "truco/res/GUI/animation/", "name": "wenziguang4.png", "md5": "2f9b2dc4eaaaed611d193263a26e1831","size":10965},
{"path": "truco/res/GUI/animation/", "name": "wenziguang5.png", "md5": "d42db87d254d78ddee5cc5bf79e97f73","size":11981},
{"path": "truco/res/GUI/animation/", "name": "wenziguang6.png", "md5": "4d0ff0c5a4502bdb2cf8cda7660a1c00","size":13115},
{"path": "truco/res/GUI/animation/", "name": "wenziguang7.png", "md5": "305e0f3d26ae65a2ffb8776a4bc34684","size":11765},
{"path": "truco/res/GUI/animation/", "name": "wenziguang8.png", "md5": "52b8d75d462a4411db31bebba197a210","size":10029},
{"path": "truco/res/GUI/animation/", "name": "wenziguang9.png", "md5": "050420c0d6d76a621e230ec5fb51b749","size":8674},
{"path": "truco/res/GUI/animation/", "name": "xipaiqiepai_1.png", "md5": "d62797f8dc41f612fee0edac1d928d39","size":3197},
{"path": "truco/res/GUI/animation/", "name": "xipaiqiepai_10.png", "md5": "36ce8a028de69957e94c6ac972a24d99","size":5812},
{"path": "truco/res/GUI/animation/", "name": "xipaiqiepai_2.png", "md5": "70b8f75f54cab927b4f08055128676be","size":3779},
{"path": "truco/res/GUI/animation/", "name": "xipaiqiepai_3.png", "md5": "002ceb8883b96078ba5809fe3d167fd8","size":4602},
{"path": "truco/res/GUI/animation/", "name": "xipaiqiepai_4.png", "md5": "62ce3674dae4bd0d1f9768c05a0385cc","size":6869},
{"path": "truco/res/GUI/animation/", "name": "xipaiqiepai_5.png", "md5": "c521a85090108d9f7ae599108efbac24","size":6595},
{"path": "truco/res/GUI/animation/", "name": "xipaiqiepai_6.png", "md5": "79bbc07a2f886275c57b680e64b41a09","size":6257},
{"path": "truco/res/GUI/animation/", "name": "xipaiqiepai_7.png", "md5": "b2098633e9b5a774169a598c41885cb6","size":5465},
{"path": "truco/res/GUI/animation/", "name": "xipaiqiepai_8.png", "md5": "1b0c95b5ec0fe15cde1c3ae493159ab8","size":5810},
{"path": "truco/res/GUI/animation/", "name": "xipaiqiepai_9.png", "md5": "0f8b6343f39d59df663799133ec02b1a","size":1120},
{"path": "truco/res/GUI/expression/", "name": "Touco_biaoqing_biaoqingdi_bg_9s.png", "md5": "64dc1ac8544227a14672c15b060665d2","size":9897},
{"path": "truco/res/GUI/expression/", "name": "Touco_biaoqing_biaoqing_biaoqing1_icon.png", "md5": "f04db002d6cd116d42f0b7ead9756068","size":820},
{"path": "truco/res/GUI/expression/", "name": "Touco_biaoqing_biaoqing_biaoqing2_icon.png", "md5": "b503a15bf8d0f7d5243b19b39d89908b","size":2409},
{"path": "truco/res/GUI/expression/", "name": "Touco_biaoqing_biaoqing_fengexian.png", "md5": "4197920a7d045f12eb404cd171c5449f","size":128},
{"path": "truco/res/GUI/expression/", "name": "Touco_biaoqing_biaoqing_liaotian1_icon.png", "md5": "82ee95bc647b3e7412920f3a67905ef7","size":577},
{"path": "truco/res/GUI/expression/", "name": "Touco_biaoqing_biaoqing_liaotian2_icon.png", "md5": "b50b6ce402c2ec2dcdf6c06d7b524e78","size":1408},
{"path": "truco/res/GUI/expression/", "name": "Touco_biaoqing_biaoqing_mofabiaoqing1.png", "md5": "2a538cb01e42f4eccfe325aea7d24388","size":4365},
{"path": "truco/res/GUI/expression/", "name": "Touco_biaoqing_biaoqing_mofabiaoqing10.png", "md5": "ed304b4cf98f4fb95261e7d70a231f92","size":17801},
{"path": "truco/res/GUI/expression/", "name": "Touco_biaoqing_biaoqing_mofabiaoqing11.png", "md5": "60ac07a48168c896893706cfb4462d0a","size":5600},
{"path": "truco/res/GUI/expression/", "name": "Touco_biaoqing_biaoqing_mofabiaoqing12.png", "md5": "305b8a5a9c48046cb559cd0bbe737bd7","size":6232},
{"path": "truco/res/GUI/expression/", "name": "Touco_biaoqing_biaoqing_mofabiaoqing2.png", "md5": "1faf405a0970ef3b345b0e6dc8f03f94","size":5747},
{"path": "truco/res/GUI/expression/", "name": "Touco_biaoqing_biaoqing_mofabiaoqing3.png", "md5": "dad5da62970022417aa0e5897a5ac6d1","size":5154},
{"path": "truco/res/GUI/expression/", "name": "Touco_biaoqing_biaoqing_mofabiaoqing4.png", "md5": "5b5bbaf4008836bd0ad3647a51e45859","size":4672},
{"path": "truco/res/GUI/expression/", "name": "Touco_biaoqing_biaoqing_mofabiaoqing5.png", "md5": "729d5f77addc89c165823363716c3718","size":4624},
{"path": "truco/res/GUI/expression/", "name": "Touco_biaoqing_biaoqing_mofabiaoqing6.png", "md5": "f73ec07db73fe2d42b1be924a02bc5ff","size":4365},
{"path": "truco/res/GUI/expression/", "name": "Touco_biaoqing_biaoqing_mofabiaoqing7.png", "md5": "5df69579f01e35e2c4cd51dbfab25554","size":4579},
{"path": "truco/res/GUI/expression/", "name": "Touco_biaoqing_biaoqing_mofabiaoqing8.png", "md5": "a3a2213333f0ca0a250a9660669a4882","size":5052},
{"path": "truco/res/GUI/expression/", "name": "Touco_biaoqing_biaoqing_mofabiaoqing9.png", "md5": "f759690d21b36672a145c42bc318fad4","size":4052},
{"path": "truco/res/GUI/expression/", "name": "Touco_biaoqing_biaoqing_putongbiaoqing1.png", "md5": "f06cdae9a02de2318ef16a582bd1b10e","size":3084},
{"path": "truco/res/GUI/expression/", "name": "Touco_biaoqing_biaoqing_putongbiaoqing10.png", "md5": "a79719b0ecf5e7e04a89eb8328e296b7","size":3910},
{"path": "truco/res/GUI/expression/", "name": "Touco_biaoqing_biaoqing_putongbiaoqing11.png", "md5": "3cc95fc08c5a832adbc924ef961d7723","size":3935},
{"path": "truco/res/GUI/expression/", "name": "Touco_biaoqing_biaoqing_putongbiaoqing12.png", "md5": "ac3917a6fedbdab80f91ce46e1a67566","size":4161},
{"path": "truco/res/GUI/expression/", "name": "Touco_biaoqing_biaoqing_putongbiaoqing2.png", "md5": "e66cfec5fa06ffba54b7add5e70e7892","size":2987},
{"path": "truco/res/GUI/expression/", "name": "Touco_biaoqing_biaoqing_putongbiaoqing3.png", "md5": "5d6a1fb204b60bf59cd9e6553e11045e","size":3043},
{"path": "truco/res/GUI/expression/", "name": "Touco_biaoqing_biaoqing_putongbiaoqing4.png", "md5": "495d627cedac383894b68beafb70b902","size":2654},
{"path": "truco/res/GUI/expression/", "name": "Touco_biaoqing_biaoqing_putongbiaoqing5.png", "md5": "fd93df821411224524a0924ad18c5c39","size":2351},
{"path": "truco/res/GUI/expression/", "name": "Touco_biaoqing_biaoqing_putongbiaoqing6.png", "md5": "38821e447b5eba4e6d555e767692a13e","size":3184},
{"path": "truco/res/GUI/expression/", "name": "Touco_biaoqing_biaoqing_putongbiaoqing7.png", "md5": "9a899dc83c18339147ee80b0f75d2d37","size":2650},
{"path": "truco/res/GUI/expression/", "name": "Touco_biaoqing_biaoqing_putongbiaoqing8.png", "md5": "3c3bd2e7669e3bd00df095d361b4c903","size":3497},
{"path": "truco/res/GUI/expression/", "name": "Touco_biaoqing_biaoqing_putongbiaoqing9.png", "md5": "37e96eb7efa68b9a6df548d2b0478f37","size":3410},
{"path": "truco/res/GUI/expression/", "name": "Touco_biaoqing_biaoqing_qieye1.png", "md5": "08966b63c181039ad9e55f4051aff565","size":1568},
{"path": "truco/res/GUI/expression/", "name": "Touco_biaoqing_biaoqing_qieye2.png", "md5": "524d2c33259feb3cffbe9103e198c130","size":4434},
{"path": "truco/res/GUI/expression/", "name": "Touco_biaoqing_hudongdi_bg_9s.png", "md5": "7b4b814bb6fa74e426d8abead180efc9","size":13109},
{"path": "truco/res/GUI/expression/", "name": "Touco_biaoqing_hudong_biaoqing1.png", "md5": "bdd3aa63de6b300decac7af1a819f82c","size":2357},
{"path": "truco/res/GUI/expression/", "name": "Touco_biaoqing_hudong_biaoqing10.png", "md5": "1ae1212054ec94426df316013350e806","size":2114},
{"path": "truco/res/GUI/expression/", "name": "Touco_biaoqing_hudong_biaoqing2.png", "md5": "88cb3c9ae54d405d53596f5f8316f2d3","size":1353},
{"path": "truco/res/GUI/expression/", "name": "Touco_biaoqing_hudong_biaoqing3.png", "md5": "18ceb0ade471dea760747ebbb455f384","size":4492},
{"path": "truco/res/GUI/expression/", "name": "Touco_biaoqing_hudong_biaoqing4.png", "md5": "01946cfb9ca8ecdb6e1fc09ce3f289c3","size":4175},
{"path": "truco/res/GUI/expression/", "name": "Touco_biaoqing_hudong_biaoqing5.png", "md5": "958a1bad57e5a737793086d872548eca","size":3151},
{"path": "truco/res/GUI/expression/", "name": "Touco_biaoqing_hudong_biaoqing6.png", "md5": "6b68d4ac753ae182f7d28a25c8699527","size":2194},
{"path": "truco/res/GUI/expression/", "name": "Touco_biaoqing_hudong_biaoqing7.png", "md5": "058a6ed897251663fa608135f3eb3bdf","size":2038},
{"path": "truco/res/GUI/expression/", "name": "Touco_biaoqing_hudong_biaoqing8.png", "md5": "8eb03a8820ae975f5b49d96127b85e4a","size":2557},
{"path": "truco/res/GUI/expression/", "name": "Touco_biaoqing_hudong_biaoqing9.png", "md5": "5d13c4d74bc381a8f79972f7e44b4c51","size":4826},
{"path": "truco/res/GUI/expression/", "name": "Touco_biaoqing_hudong_biaoqingdi.png", "md5": "d3ea892aabdc2b0d00b363a52451ca14","size":908},
{"path": "truco/res/GUI/expression/", "name": "Touco_biaoqing_hudong_jinbi.png", "md5": "a7f1ac50186867ac0592aaee45d11e57","size":1923},
{"path": "truco/res/GUI/expression/", "name": "Touco_biaoqing_hudong_jindu.png", "md5": "84435040c8af6f57681308b2e79de9d6","size":1706},
{"path": "truco/res/GUI/expression/", "name": "Touco_liaotian_tipskuang1_9s.png", "md5": "0d7f879310a42374f8576c2720ceb7aa","size":1022},
{"path": "truco/res/GUI/expression/", "name": "Touco_liaotian_tipskuang2_9s.png", "md5": "70af41e71b1fd6f612e98335a479fddc","size":930},
{"path": "truco/res/GUI/expression/", "name": "Touco_liaotian_tipskuang3_9s.png", "md5": "c44306d3b3cb03c108ed555ed34dbebe","size":894},
{"path": "truco/res/GUI/help/", "name": "truco_gz_bt.png", "md5": "7214bdc069638dc3d5aa752e806608c8","size":2428},
{"path": "truco/res/GUI/help/", "name": "truco_gz_dk.png", "md5": "4c0246f9f9a9ac7ed4d58aeb39a351a2","size":11552},
{"path": "truco/res/GUI/help/", "name": "truco_gz_fydk1.png", "md5": "60d0acf6bb90286b636438abe8c40b92","size":1241},
{"path": "truco/res/GUI/help/", "name": "truco_gz_fydk2.png", "md5": "443d01381a8a06500d2411d3c9713c99","size":2402},
{"path": "truco/res/GUI/help/", "name": "truco_gz_gb.png", "md5": "ff1ff32e526667d40b102582187b6a2e","size":1380},
{"path": "truco/res/GUI/help/", "name": "truco_gz_sm1.png", "md5": "17603707c0b74e4c4a9f01d852baa9cf","size":100663},
{"path": "truco/res/GUI/help/", "name": "truco_gz_sm2.png", "md5": "e8436cfa334def827d8d61f4da507178","size":100422},
{"path": "truco/res/GUI/help/", "name": "truco_gz_sm3.png", "md5": "e2950fe6170d26a613951c566de0bda8","size":75018},
{"path": "truco/res/GUI/poker/", "name": "truco_big_0.png", "md5": "23409eda0258d6a9e7f1de54cf86aa3a","size":2782},
{"path": "truco/res/GUI/poker/", "name": "truco_big_1.png", "md5": "59fddecc8ba6d665cb7b4f188521f764","size":2787},
{"path": "truco/res/GUI/poker/", "name": "truco_big_11_0.png", "md5": "d08223ea8f494953f0f001cce07873e0","size":15448},
{"path": "truco/res/GUI/poker/", "name": "truco_big_11_1.png", "md5": "3bb34f48b0dd1ab69397cf0b55dc8a46","size":15535},
{"path": "truco/res/GUI/poker/", "name": "truco_big_12_0.png", "md5": "11892ea9ccac4be025e2e380e64de6bd","size":16451},
{"path": "truco/res/GUI/poker/", "name": "truco_big_12_1.png", "md5": "a53c54c65b58b7fc92b46a08eec64090","size":15860},
{"path": "truco/res/GUI/poker/", "name": "truco_big_13_0.png", "md5": "ac43391e5f7ccbd1e6acb2b81851179e","size":15474},
{"path": "truco/res/GUI/poker/", "name": "truco_big_13_1.png", "md5": "500d5ec2e21b5f4f7f18955770f5a016","size":15437},
{"path": "truco/res/GUI/poker/", "name": "truco_big_2.png", "md5": "d5500bf012ee2816fda502ac130d1dd4","size":3199},
{"path": "truco/res/GUI/poker/", "name": "truco_big_3.png", "md5": "625d1927fca1545145dcf97e47b5923d","size":2667},
{"path": "truco/res/GUI/poker/", "name": "truco_black_1.png", "md5": "a10ef6971d53b916d757d1b0221a50aa","size":1536},
{"path": "truco/res/GUI/poker/", "name": "truco_black_10.png", "md5": "74fefdf6bbd0bf901167bf190cc8c91f","size":1365},
{"path": "truco/res/GUI/poker/", "name": "truco_black_11.png", "md5": "32c410e80cf3e6333a7b207ca11ffbde","size":1264},
{"path": "truco/res/GUI/poker/", "name": "truco_black_12.png", "md5": "ec1b43c61bce04c4fc51684626ce7810","size":1457},
{"path": "truco/res/GUI/poker/", "name": "truco_black_13.png", "md5": "61df0a4b8decd139a558e4fd75d15a33","size":1454},
{"path": "truco/res/GUI/poker/", "name": "truco_black_2.png", "md5": "b803e7b920141f131fa2b78537d49069","size":1467},
{"path": "truco/res/GUI/poker/", "name": "truco_black_3.png", "md5": "23eb2c89f4aee29a0ad47e1b69ca6b3d","size":1439},
{"path": "truco/res/GUI/poker/", "name": "truco_black_4.png", "md5": "9afd859bc0d1769d437601e9b844c1ca","size":1353},
{"path": "truco/res/GUI/poker/", "name": "truco_black_5.png", "md5": "d54265bf95a03fb3619d86035abe39a0","size":1479},
{"path": "truco/res/GUI/poker/", "name": "truco_black_6.png", "md5": "435dae1cb4f693798d7f783d7a99f727","size":1546},
{"path": "truco/res/GUI/poker/", "name": "truco_black_7.png", "md5": "08a825f5b28d30402406f63530a1a441","size":1356},
{"path": "truco/res/GUI/poker/", "name": "truco_black_8.png", "md5": "47890a9d2de80250432069fc47770ab8","size":1546},
{"path": "truco/res/GUI/poker/", "name": "truco_black_9.png", "md5": "19ddc08e71f65dfda14e5d740397d9ae","size":1567},
{"path": "truco/res/GUI/poker/", "name": "truco_poker_back.png", "md5": "468bf600a4f294effb48ce1bd7901a7e","size":8322},
{"path": "truco/res/GUI/poker/", "name": "truco_poker_effect.png", "md5": "6ebe098c3b8d2f8a3df6b3a42de2fabc","size":2669},
{"path": "truco/res/GUI/poker/", "name": "truco_poker_front.png", "md5": "0528d0787a59aaf0020027f8efab921e","size":2106},
{"path": "truco/res/GUI/poker/", "name": "truco_poker_front_y.png", "md5": "9bc2851c0951ef6bad7b66f4c49fa4d0","size":7834},
{"path": "truco/res/GUI/poker/", "name": "truco_poker_gray.png", "md5": "6a5b1fcacf8ea80c41522bdb075edda4","size":1366},
{"path": "truco/res/GUI/poker/", "name": "truco_red_1.png", "md5": "5b6e17ba2881ec5cc9a408305ea032c0","size":1702},
{"path": "truco/res/GUI/poker/", "name": "truco_red_10.png", "md5": "9c08ef6c182ebd0c570a95f9c8023d42","size":1461},
{"path": "truco/res/GUI/poker/", "name": "truco_red_11.png", "md5": "94da23348115d813d4ade28cf1fae8e7","size":1270},
{"path": "truco/res/GUI/poker/", "name": "truco_red_12.png", "md5": "e5e3341a6349ee434bbac0786d6d8955","size":1514},
{"path": "truco/res/GUI/poker/", "name": "truco_red_13.png", "md5": "dcb3dd1ba32d391982fa7220e2138393","size":1495},
{"path": "truco/res/GUI/poker/", "name": "truco_red_2.png", "md5": "8358d06604fa0b21494461d2f4484fe4","size":1554},
{"path": "truco/res/GUI/poker/", "name": "truco_red_3.png", "md5": "6a3859d37eade361d3978ab2e34e055e","size":1561},
{"path": "truco/res/GUI/poker/", "name": "truco_red_4.png", "md5": "8aaffee5346a6d3e0e057379eb83f1df","size":1365},
{"path": "truco/res/GUI/poker/", "name": "truco_red_5.png", "md5": "6f0d104747353d3facdd8a2fa082ee95","size":1550},
{"path": "truco/res/GUI/poker/", "name": "truco_red_6.png", "md5": "9be40e5090f31e740a356ef5060baddf","size":1695},
{"path": "truco/res/GUI/poker/", "name": "truco_red_7.png", "md5": "ca07cfa683a83716325fde2f505ecbd1","size":1398},
{"path": "truco/res/GUI/poker/", "name": "truco_red_8.png", "md5": "e7ebd47e5bf2c428c6c9622942e15995","size":1661},
{"path": "truco/res/GUI/poker/", "name": "truco_red_9.png", "md5": "ef7cf5838a0c9eb06e781a0f837819a8","size":1734},
{"path": "truco/res/GUI/poker/", "name": "truco_small_0.png", "md5": "76f8190f455e133dbef9da0bc928a49f","size":1423},
{"path": "truco/res/GUI/poker/", "name": "truco_small_1.png", "md5": "89ae7f9f9b74b546760b7d56f8fa65c8","size":1444},
{"path": "truco/res/GUI/poker/", "name": "truco_small_2.png", "md5": "bca0f2db6b3202e054f3b8d04d7d7a09","size":1396},
{"path": "truco/res/GUI/poker/", "name": "truco_small_3.png", "md5": "98cc8cb381db696febbc3be3e0471d8c","size":1434},
{"path": "truco/res/GUI/watermask/", "name": "truco_wm_1.png", "md5": "dff285b7412d59d045fd34fa10ab8b78","size":1402},
{"path": "truco/res/GUI/watermask/", "name": "truco_wm_11.png", "md5": "20070827867e581192871428fd1384d8","size":1428},
{"path": "truco/res/GUI/watermask/", "name": "truco_wm_12.png", "md5": "3ee03e21510519c2a2cd358b9efc9df6","size":1510},
{"path": "truco/res/GUI/watermask/", "name": "truco_wm_13.png", "md5": "35e1e114b13a71e5639b525ee1a61960","size":1425},
{"path": "truco/res/GUI/watermask/", "name": "truco_wm_2.png", "md5": "2d7a955bd0e05ae5365ab90743d76d96","size":1431},
{"path": "truco/res/GUI/watermask/", "name": "truco_wm_3.png", "md5": "9087d9199f1613dea926e022b4a348f4","size":1398},
{"path": "truco/res/GUI/watermask/", "name": "truco_wm_fk.png", "md5": "bb05507df942b1ccbe6304c2748beacf","size":1353},
{"path": "truco/res/GUI/watermask/", "name": "truco_wm_ht.png", "md5": "3f88e2223ceeea7ec3bec3ca6771a288","size":1385},
{"path": "truco/res/GUI/watermask/", "name": "truco_wm_hx.png", "md5": "98c9f78a9d361f98288ceac42a666472","size":1329},
{"path": "truco/res/GUI/watermask/", "name": "truco_wm_mh.png", "md5": "aad7d9b8fcab2f1f0e8a0be5c52e92ad","size":1404},
{"path": "truco/res/GUI/watermask/", "name": "truco_wm_name.png", "md5": "0521064b80a53fb6edf03ae66686a737","size":2493},
{"path": "truco/res/sound_res/", "name": "truco_action_accept_1.mp3", "md5": "808181c58664ebca37483771e0c01c40","size":22151},
{"path": "truco/res/sound_res/", "name": "truco_action_accept_2.mp3", "md5": "3156b3aee3902a2f4b1791d640e4af76","size":38452},
{"path": "truco/res/sound_res/", "name": "truco_action_giveup_1.mp3", "md5": "6a300230451cb3ddd94e65ba36dfecdb","size":39288},
{"path": "truco/res/sound_res/", "name": "truco_action_giveup_2.mp3", "md5": "b5605a999e20588dbc6ab24a55eca154","size":31764},
{"path": "truco/res/sound_res/", "name": "truco_action_truco_1.mp3", "md5": "4e9253151ac113a16607dcb36662209c","size":43049},
{"path": "truco/res/sound_res/", "name": "truco_action_truco_2.mp3", "md5": "0f8f37628cc402875bf61f849ac4f846","size":43049},
{"path": "truco/res/sound_res/", "name": "truco_action_truco_3.mp3", "md5": "7030388d2a499d1f54b3de2ee50a58fb","size":48065},
{"path": "truco/res/sound_res/", "name": "truco_action_truco_4.mp3", "md5": "e74a7eb36dfa02ce46f4b3e43b8d0b2c","size":50155},
{"path": "truco/res/sound_res/", "name": "truco_bg_music.mp3", "md5": "dd90f8d76117dcd1c789d28cefd79a70","size":635564},
{"path": "truco/res/sound_res/", "name": "truco_flip_card.mp3", "md5": "e9f1bbe7a27008f1f67638aa93776b7e","size":4597},
{"path": "truco/res/sound_res/", "name": "truco_out_card.mp3", "md5": "0ebc7f2b054eaa1b708af78ff9cd3306","size":13374},
{"path": "truco/res/sound_res/", "name": "truco_out_trump_card.mp3", "md5": "b677868b48f0c04b776e7f8f05e8086f","size":7523},
{"path": "truco/res/sound_res/", "name": "truco_out_trump_card_1.mp3", "md5": "7ba4664653e9d8e36509f36aaa05ad88","size":40542},
{"path": "truco/res/sound_res/", "name": "truco_recovery_card.mp3", "md5": "6e0ded163e24d9d7fb2ff4177ca43a92","size":5496},
{"path": "truco/res/sound_res/", "name": "truco_result_coin_loseOut.mp3", "md5": "db13c77b36452d928837d458bca3e03c","size":21733},
{"path": "truco/res/sound_res/", "name": "truco_result_coin_winIn.mp3", "md5": "877b78c96d050cf03d65d7911942c8e9","size":32736},
{"path": "truco/res/sound_res/", "name": "truco_result_lose.mp3", "md5": "3cc5a141af7dfe798b1dc390d53a30f1","size":10908},
{"path": "truco/res/sound_res/", "name": "truco_result_win.mp3", "md5": "0b350398a32ec8f39e0414ba16d52046","size":21240},
{"path": "truco/res/sound_res/", "name": "truco_round_win_effect.mp3", "md5": "9b7aa1a06eeb3a25d4791ef1645f67c9","size":31764},
{"path": "truco/res/sound_res/", "name": "truco_score_changed.mp3", "md5": "dcf3adc4904d05365be96370e9bfcb58","size":33018},
{"path": "truco/res/sound_res/", "name": "truco_self_operation.mp3", "md5": "ff8c6816d5f1be58f902029846efab4a","size":41590},
{"path": "truco/res/sound_res/", "name": "truco_start_enter.mp3", "md5": "59612e35c4159f5b1cb470d1912cde8a","size":16200},
{"path": "truco/res/sound_res/", "name": "truco_start_flushcard.mp3", "md5": "ab15fa1bec14bd252d67ee7e201ba9fb","size":44721},
{"path": "truco/res/sound_res/", "name": "truco_start_pemove.mp3", "md5": "c8b0e52f8c3c0f1ef85cb2043c65b9e9","size":4597},
{"path": "truco/res/sound_res/", "name": "truco_start_sendcard.mp3", "md5": "26841a485536e35f568f2dbc0542912f","size":6896},
{"path": "truco/res/sound_res/", "name": "truco_start_vs.mp3", "md5": "cea658da2213dc46b4df9e0086077a86","size":36362},
{"path": "truco/res/sound_res/", "name": "truco_time_down.mp3", "md5": "c15f728dffaa1d595c2a9a9ca7e3adfb","size":9673},
{"path": "truco/res/spine/hudong/", "name": "diaoyu.atlas", "md5": "ce8b56c04a9fb9ec3d9b041cda1c0257","size":5960},
{"path": "truco/res/spine/hudong/", "name": "diaoyu.json", "md5": "7dea9c4a685e6f52c1b237aeb52ebaa8","size":85920},
{"path": "truco/res/spine/hudong/", "name": "diaoyu.png", "md5": "20be7c2f17f0ea3712086bf6ec1d6ba1","size":67862},
{"path": "truco/res/spine/hudong/", "name": "huishouguzhang.atlas", "md5": "a9361b6ed0805e91aeb38fd27b0af06c","size":949},
{"path": "truco/res/spine/hudong/", "name": "huishouguzhang.json", "md5": "620676e576d2ca248b45c41b5cab5543","size":23167},
{"path": "truco/res/spine/hudong/", "name": "huishouguzhang.png", "md5": "84a58e4357006acae5b9efabb39b0d24","size":5476},
{"path": "truco/res/spine/hudong/", "name": "jiateling.atlas", "md5": "3f894a1821577a998b7c86d855206885","size":2772},
{"path": "truco/res/spine/hudong/", "name": "jiateling.json", "md5": "e953b90b1673f48baebb017ed7f4ff27","size":53809},
{"path": "truco/res/spine/hudong/", "name": "jiateling.png", "md5": "22ac62554f7c637de8ee2284bd9847a4","size":50637},
{"path": "truco/res/spine/hudong/", "name": "motou.atlas", "md5": "7caafc98c0a4fca6d0e5800e2673d6c2","size":258},
{"path": "truco/res/spine/hudong/", "name": "motou.json", "md5": "b0cd57c4958e336e9bc51927137e41b7","size":10087},
{"path": "truco/res/spine/hudong/", "name": "motou.png", "md5": "92ba4707bf6f21c003b6659bf4986b7c","size":2728},
{"path": "truco/res/spine/hudong/", "name": "penbei.atlas", "md5": "7a66f6c6349cc9e03483a566a4e90ec9","size":715},
{"path": "truco/res/spine/hudong/", "name": "penbei.json", "md5": "8d80fcd9ffbedc1f3697b04de40afed5","size":35553},
{"path": "truco/res/spine/hudong/", "name": "penbei.png", "md5": "ed1b0450ab21f363c7eabfd86561fd5b","size":3140},
{"path": "truco/res/spine/hudong/", "name": "qiaji.atlas", "md5": "487076705cb0b3af98604c39bda98b23","size":2605},
{"path": "truco/res/spine/hudong/", "name": "qiaji.json", "md5": "ba3ba97a52e04d2510f7971c2685c94a","size":5462},
{"path": "truco/res/spine/hudong/", "name": "qiaji.png", "md5": "393ea034faec2b75cbcbbd61c2470140","size":66576},
{"path": "truco/res/spine/hudong/", "name": "qinwen.atlas", "md5": "b5ae897904a3a44d7a68686ae0498c68","size":1791},
{"path": "truco/res/spine/hudong/", "name": "qinwen.json", "md5": "79a40d2fc49b30f962e27869f7c4ff50","size":10211},
{"path": "truco/res/spine/hudong/", "name": "qinwen.png", "md5": "fe8f8a9ea6431205115e3473fe4ecd4e","size":28383},
{"path": "truco/res/spine/hudong/", "name": "rengshi.atlas", "md5": "1b198d99c5dee5ef1c0e19d2dd65d4b1","size":1905},
{"path": "truco/res/spine/hudong/", "name": "rengshi.json", "md5": "f5804b58ca1ee9173d1f599d74438cb8","size":4581},
{"path": "truco/res/spine/hudong/", "name": "rengshi.png", "md5": "febd71bb51a855e67322dc1d15b1a42c","size":32579},
{"path": "truco/res/spine/hudong/", "name": "weiyu.atlas", "md5": "527962a28a6529fabaad3049772a1c67","size":2531},
{"path": "truco/res/spine/hudong/", "name": "weiyu.json", "md5": "ad904e143a1d379d886e4b4838ed6bd8","size":18455},
{"path": "truco/res/spine/hudong/", "name": "weiyu.png", "md5": "4f42e90582948c0ecc10ccb7c1147e91","size":50001},
{"path": "truco/res/spine/hudong/", "name": "zhadan.atlas", "md5": "fe08f8dbeea744ca1610d0cd2cebd26b","size":2239},
{"path": "truco/res/spine/hudong/", "name": "zhadan.json", "md5": "4763173fa6b8422ed6d97e8f8f73048a","size":5121},
{"path": "truco/res/spine/hudong/", "name": "zhadan.png", "md5": "3d23e67efdf0b3b0307a8c6da0a63990","size":46779},
{"path": "truco/res/spine/magic/", "name": "mf_face01_ske.atlas", "md5": "b545973db01db5881104f5acb903af92","size":1112},
{"path": "truco/res/spine/magic/", "name": "mf_face01_ske.json", "md5": "8cbbe9266e70d5ea86fc8eba5a6a99c2","size":2091},
{"path": "truco/res/spine/magic/", "name": "mf_face01_ske.png", "md5": "db2408cbed3824172bda74cd35b70769","size":35654},
{"path": "truco/res/spine/magic/", "name": "mf_face02_ske.atlas", "md5": "ea7095d49171cacc9f069795a4059f99","size":1124},
{"path": "truco/res/spine/magic/", "name": "mf_face02_ske.json", "md5": "a73b7d0ba9203801f917c63f7fff3d8f","size":2098},
{"path": "truco/res/spine/magic/", "name": "mf_face02_ske.png", "md5": "37cc0f22278ef8b075e7d025821c797c","size":51075},
{"path": "truco/res/spine/magic/", "name": "mf_face03_ske.atlas", "md5": "341f7f297096e93bfa71bc49bfd0be84","size":1598},
{"path": "truco/res/spine/magic/", "name": "mf_face03_ske.json", "md5": "177905571d5543ae5472feb71dfaf45d","size":2921},
{"path": "truco/res/spine/magic/", "name": "mf_face03_ske.png", "md5": "a216ff0ebbc7f5f30c8d7287c6d3db3e","size":35655},
{"path": "truco/res/spine/magic/", "name": "mf_face04_ske.atlas", "md5": "e972fb1f2a6315a05b17bbf057b414d3","size":1131},
{"path": "truco/res/spine/magic/", "name": "mf_face04_ske.json", "md5": "80a22a6861ea620452431db95ddad23f","size":2096},
{"path": "truco/res/spine/magic/", "name": "mf_face04_ske.png", "md5": "27dfd0a556c391b2f8a70ebc378018bd","size":35028},
{"path": "truco/res/spine/magic/", "name": "mf_face05_ske.atlas", "md5": "746bc637e6feab28dfbceb1c7feb05b6","size":697},
{"path": "truco/res/spine/magic/", "name": "mf_face05_ske.json", "md5": "3b994507d6236e34691aa41e2123e6c1","size":1424},
{"path": "truco/res/spine/magic/", "name": "mf_face05_ske.png", "md5": "83b50fe31699af56af41c9c012cdf197","size":21872},
{"path": "truco/res/spine/magic/", "name": "mf_face06_ske.atlas", "md5": "979574465918c25bd46079fccdc0bacd","size":1341},
{"path": "truco/res/spine/magic/", "name": "mf_face06_ske.json", "md5": "1439b021940ad9c41085cdf8da90e7b0","size":2430},
{"path": "truco/res/spine/magic/", "name": "mf_face06_ske.png", "md5": "752e27a1fc912b843ed3c9618435629b","size":40430},
{"path": "truco/res/spine/magic/", "name": "mf_face07_ske.atlas", "md5": "2cacba8663996a295d1e93964d7c4a4d","size":499},
{"path": "truco/res/spine/magic/", "name": "mf_face07_ske.json", "md5": "82f7ea1aee4942ea611e2d49484db789","size":1093},
{"path": "truco/res/spine/magic/", "name": "mf_face07_ske.png", "md5": "55cf4f0e0ea0f49b2164d9dd8b604ca9","size":14414},
{"path": "truco/res/spine/magic/", "name": "mf_face08_ske.atlas", "md5": "60d223b867084177b02d2bbc81d0b80f","size":1124},
{"path": "truco/res/spine/magic/", "name": "mf_face08_ske.json", "md5": "4123284238456f8928b42331d2cd899d","size":2093},
{"path": "truco/res/spine/magic/", "name": "mf_face08_ske.png", "md5": "f543474cb4c6fe7ddf752c14a65e9dff","size":32833},
{"path": "truco/res/spine/magic/", "name": "mf_face09_ske.atlas", "md5": "a73db457864984dd7c7ed325ebc20efb","size":1339},
{"path": "truco/res/spine/magic/", "name": "mf_face09_ske.json", "md5": "d3564eeb6d6e3544813aebf78bc63a78","size":2433},
{"path": "truco/res/spine/magic/", "name": "mf_face09_ske.png", "md5": "5976e59c07e60aa4f8bb10e5f67faad9","size":34392},
{"path": "truco/res/spine/magic/", "name": "mf_face10_ske.atlas", "md5": "58cb9404285d33baf74601dc3a99a736","size":1335},
{"path": "truco/res/spine/magic/", "name": "mf_face10_ske.json", "md5": "5c7331353cd46820e526edda6b404fa1","size":2433},
{"path": "truco/res/spine/magic/", "name": "mf_face10_ske.png", "md5": "4e0e3200081d454a9a6d898b2c5ccdd1","size":50694},
{"path": "truco/res/spine/magic/", "name": "mf_face11_ske.atlas", "md5": "6232718249a87cb598981cccd87e4aac","size":608},
{"path": "truco/res/spine/magic/", "name": "mf_face11_ske.json", "md5": "f592bb0183859be87896f9c6f6c3e597","size":1263},
{"path": "truco/res/spine/magic/", "name": "mf_face11_ske.png", "md5": "445c6c44de02c509539997730f09cace","size":20691},
{"path": "truco/res/spine/magic/", "name": "mf_face12_ske.atlas", "md5": "96110c20845640ec426c64b568697a7b","size":1241},
{"path": "truco/res/spine/magic/", "name": "mf_face12_ske.json", "md5": "b2fc98eacacae5963f62d943da23cead","size":2268},
{"path": "truco/res/spine/magic/", "name": "mf_face12_ske.png", "md5": "4c5d3d129e32c90434bc247de6d35db8","size":54813},
{"path": "truco/res/spine/magic/", "name": "mf_face13_ske.atlas", "md5": "40e04755fe39ff68817dfc18796ec12b","size":2202},
{"path": "truco/res/spine/magic/", "name": "mf_face13_ske.json", "md5": "bb592a14dae91729b29879af30a2a9fa","size":3791},
{"path": "truco/res/spine/magic/", "name": "mf_face13_ske.png", "md5": "db2dc9afeb30716f186f28007d8e1537","size":75103},
{"path": "truco/res/spine/normal/", "name": "face10_ske.atlas", "md5": "54d6195db1dd2912d8d553b47c8c9f2a","size":1288},
{"path": "truco/res/spine/normal/", "name": "face10_ske.json", "md5": "4ce539509661efe180a764a51a65aa81","size":2435},
{"path": "truco/res/spine/normal/", "name": "face10_ske.png", "md5": "2cb86b062a2dbf9d89a9fa1bff4e47d0","size":15057},
{"path": "truco/res/spine/normal/", "name": "face11_ske.atlas", "md5": "97848a0977069c2fc4ea05763ec29eaf","size":1186},
{"path": "truco/res/spine/normal/", "name": "face11_ske.json", "md5": "3b625315bd4ab3ae2f3c9b756b3404b3","size":2265},
{"path": "truco/res/spine/normal/", "name": "face11_ske.png", "md5": "3823bd8f0ac57df4520320569ddd6adc","size":16796},
{"path": "truco/res/spine/normal/", "name": "face12_ske.atlas", "md5": "74746a0f354201f0d3b5cd5cde4a94e7","size":1083},
{"path": "truco/res/spine/normal/", "name": "face12_ske.json", "md5": "b3b067e308f812375441c3720093ca05","size":2097},
{"path": "truco/res/spine/normal/", "name": "face12_ske.png", "md5": "1571921c3f44c898fb90865a10663059","size":17357},
{"path": "truco/res/spine/normal/", "name": "face1_ske.atlas", "md5": "45e5938583bb1548b82878c5ba8f0215","size":1072},
{"path": "truco/res/spine/normal/", "name": "face1_ske.json", "md5": "74d541218cb4b96419256611bfdc06b4","size":2065},
{"path": "truco/res/spine/normal/", "name": "face1_ske.png", "md5": "d790d4eb3336178d62dadb800bbffc26","size":10986},
{"path": "truco/res/spine/normal/", "name": "face2_ske.atlas", "md5": "d30f30173f9abc64a5d7184322ff53d2","size":1072},
{"path": "truco/res/spine/normal/", "name": "face2_ske.json", "md5": "5627cc83338570131fd45c9b1b6c68de","size":2065},
{"path": "truco/res/spine/normal/", "name": "face2_ske.png", "md5": "c13bf7747c2055222f83c0611101df47","size":13383},
{"path": "truco/res/spine/normal/", "name": "face3_ske.atlas", "md5": "fef1c0dc3544f18e6c5cc05cb2a98201","size":1072},
{"path": "truco/res/spine/normal/", "name": "face3_ske.json", "md5": "92a0511d3ef3cac35ad10e249caea657","size":2065},
{"path": "truco/res/spine/normal/", "name": "face3_ske.png", "md5": "64c0f88e79767ecb01e809299bf6e3e6","size":6964},
{"path": "truco/res/spine/normal/", "name": "face4_ske.atlas", "md5": "6c518d93261e0f2d713753d19606ac96","size":1072},
{"path": "truco/res/spine/normal/", "name": "face4_ske.json", "md5": "5a59d475fd21b410f729673c3aefd99a","size":2065},
{"path": "truco/res/spine/normal/", "name": "face4_ske.png", "md5": "a5921795e2b7fca8c8a857af7deaa5d2","size":12284},
{"path": "truco/res/spine/normal/", "name": "face5_ske.atlas", "md5": "7149a257d33fdaa1a0dc3bf486591c5b","size":1072},
{"path": "truco/res/spine/normal/", "name": "face5_ske.json", "md5": "d1a566bb436f0f55d4311a734818c7c8","size":2065},
{"path": "truco/res/spine/normal/", "name": "face5_ske.png", "md5": "b3f4a124287df54e93e42c125e4f9db2","size":8829},
{"path": "truco/res/spine/normal/", "name": "face6_ske.atlas", "md5": "956b72e7c1f00f7902e1b6934ee86491","size":1072},
{"path": "truco/res/spine/normal/", "name": "face6_ske.json", "md5": "014f9cfa9e3b69ef5f7163364976975c","size":2065},
{"path": "truco/res/spine/normal/", "name": "face6_ske.png", "md5": "97e636c9fa241f800bdb9e77cd27aa9c","size":12192},
{"path": "truco/res/spine/normal/", "name": "face7_ske.atlas", "md5": "f263dbefcdff54cc6376de188c3eea9f","size":1072},
{"path": "truco/res/spine/normal/", "name": "face7_ske.json", "md5": "1206ae470abbeb9f63bcccf8b8530a0a","size":2065},
{"path": "truco/res/spine/normal/", "name": "face7_ske.png", "md5": "5b89981cb7e5dfa579da9a383a2a9667","size":9454},
{"path": "truco/res/spine/normal/", "name": "face8_ske.atlas", "md5": "9e17ab0dcda73c349e672652be599e52","size":2484},
{"path": "truco/res/spine/normal/", "name": "face8_ske.json", "md5": "f6030decb8dc003fb30c20ce2807f776","size":4401},
{"path": "truco/res/spine/normal/", "name": "face8_ske.png", "md5": "9255467d66cf712488672aa6b27af7c9","size":35264},
{"path": "truco/res/spine/normal/", "name": "face9_ske.atlas", "md5": "f0d1e9cd43fd126556ebccf8d1943f11","size":1072},
{"path": "truco/res/spine/normal/", "name": "face9_ske.json", "md5": "be5da28a468ef14527ef849358897895","size":2065},
{"path": "truco/res/spine/normal/", "name": "face9_ske.png", "md5": "46a13febc70f3c6886ff0b7431ac8679","size":13113},
{"path": "truco/res/UI/", "name": "Node_feijinbidonghua.csb", "md5": "009d06325b8a229b7fc3f100c3f247ce","size":77028},
{"path": "truco/res/UI/", "name": "Node_jiesuandonghua_shengli.csb", "md5": "2b97d73616e623efbae262cba3334743","size":19724},
{"path": "truco/res/UI/", "name": "Node_jiesuandonghua_shibai.csb", "md5": "4f005d35bf9679e19cc88bc3d2327de6","size":20284},
{"path": "truco/res/UI/", "name": "Node_shangpiaofenshudian.csb", "md5": "fa1873f2b302d10f314ed8ad1b4738b5","size":7276},
{"path": "truco/res/UI/", "name": "Node_touxiangtiexiao.csb", "md5": "20078d4f141de82816fcbb78af000069","size":5500},
{"path": "truco/res/UI/", "name": "Node_vsdonghua.csb", "md5": "b6d8d937b320566ce147bd0533bed697","size":19592},
{"path": "truco/res/UI/", "name": "Node_waitTip.csb", "md5": "54357a85dbf88e8ce0bd1c11f7fe7191","size":4080},
{"path": "truco/res/UI/", "name": "Node_xipaiqiepaidonghua.csb", "md5": "4bb1be29c1a2b51de8a3e09fff2bcd3b","size":8564},
{"path": "truco/res/UI/", "name": "Node_zuidapaidachutexiao_0.csb", "md5": "3a0c36657eaf0cee3702e17aed5d8f6f","size":1528},
{"path": "truco/res/UI/", "name": "Node_zuidapaidachutexiao_1.csb", "md5": "745f428272f54be1ca646cb70180694e","size":5184},
{"path": "truco/res/UI/", "name": "TrucoBubbleLayer.csb", "md5": "67fde86fe08e5c9b5f58094e9fdf2890","size":1588},
{"path": "truco/res/UI/", "name": "TrucoBubbleNode_1.csb", "md5": "826b8f7a3921e526bfb2bc665d1cb36a","size":8372},
{"path": "truco/res/UI/", "name": "TrucoBubbleNode_2.csb", "md5": "edb19ec54f664e17e735521c0fca28e7","size":8372},
{"path": "truco/res/UI/", "name": "TrucoBubbleNode_3.csb", "md5": "6d19771989349c97e035a74b18f86bd0","size":8372},
{"path": "truco/res/UI/", "name": "TrucoButtonNode.csb", "md5": "419338099656be5d6e6c8ca9bad136d2","size":7312},
{"path": "truco/res/UI/", "name": "TrucoCardLayer.csb", "md5": "aa94be439ee917e504a7f156e2147179","size":4700},
{"path": "truco/res/UI/", "name": "TrucoCardLayer_temp.csb", "md5": "b4149fbdacbc0f422c3db20972f0a5e9","size":5708},
{"path": "truco/res/UI/", "name": "TrucoCardNode.csb", "md5": "a7c0b7d30584b71c174b462e1e0ac63b","size":3792},
{"path": "truco/res/UI/", "name": "TrucoChatNode1.csb", "md5": "6b558cf0d3553ae83e4e2ac086b419e7","size":2004},
{"path": "truco/res/UI/", "name": "TrucoChatNode2.csb", "md5": "9bd60cfc05b2a28658a7c98804fcceca","size":2004},
{"path": "truco/res/UI/", "name": "TrucoChatNode3.csb", "md5": "a8ed1bcf12860493f9863075ea482209","size":2004},
{"path": "truco/res/UI/", "name": "TrucoExpressionLayer.csb", "md5": "8cf9560f2c172916375b88a863ed889d","size":39988},
{"path": "truco/res/UI/", "name": "TrucoGameLayer.csb", "md5": "70c429dddd9d6ef01c53764a6a6cb033","size":8572},
{"path": "truco/res/UI/", "name": "TrucoHelpNode.csb", "md5": "fa144b1caceff25dcf8852584bf3df66","size":9476},
{"path": "truco/res/UI/", "name": "TrucoHuDongLayer.csb", "md5": "651b32eb2e6d77de4a6176221030da23","size":28008},
{"path": "truco/res/UI/", "name": "TrucoPlayerLayer.csb", "md5": "5037f1651aac0c32ad1786fa12c2416f","size":3288},
{"path": "truco/res/UI/", "name": "TrucoPlayerLayer_temp.csb", "md5": "6ec8ee5df9f69b8f71f115ea94e15c62","size":4644},
{"path": "truco/res/UI/", "name": "TrucoPlayerNode.csb", "md5": "c423add7ec13cfce959675893e57e5d4","size":6716},
{"path": "truco/res/UI/", "name": "TrucoScoreNode.csb", "md5": "62ca3276de37f322024fac07d1834946","size":7400},
{"path": "truco/res/UI/", "name": "TrucoTrusteeNode.csb", "md5": "bf988854f53f3d3811e9e23842c99139","size":2680},
{"path": "truco/res/UI/", "name": "TrucoWaterMarkNode.csb", "md5": "7724696416d28d71705ae0eb63d8ccef","size":5348},
{"path": "truco/res/UI/", "name": "TrucoWaterMaskNode.csb", "md5": "9f9f15b8ff8710fa745656e5e3a0b4c5","size":15000},
{"path": "truco/src/models/", "name": "CMD_Game.lua", "md5": "2f40c1c3decc91946630cb2805242887","size":15394},
{"path": "truco/src/models/", "name": "GameFrame.lua", "md5": "ffd1b1a92dfbec97879c2ced6ffc616d","size":3155},
{"path": "truco/src/models/", "name": "GameLogic.lua", "md5": "8d1fa62b88321c363ab05fc186458af4","size":7932},
{"path": "truco/src/views/", "name": "GameLayer.lua", "md5": "4b19ee7ebd4badf0eba25803815b4e49","size":16228},
{"path": "truco/src/views/layer/", "name": "TrucoBubbleLayer.lua", "md5": "6a439448e9ecc390a8b92ad0549fb266","size":9371},
{"path": "truco/src/views/layer/", "name": "TrucoButtonNode.lua", "md5": "82eff1ce18e0dc0db82c87a867c60b11","size":5725},
{"path": "truco/src/views/layer/", "name": "TrucoCardLayer.lua", "md5": "752553f28d6657197f0cd38362a6dbdb","size":29151},
{"path": "truco/src/views/layer/", "name": "TrucoCardNode.lua", "md5": "8e3389d5c3249db994053aec56b7719d","size":6254},
{"path": "truco/src/views/layer/", "name": "TrucoChatAnimNode.lua", "md5": "e4392ae867646386f57009e541ec2c42","size":12709},
{"path": "truco/src/views/layer/", "name": "TrucoChatLayer.lua", "md5": "f32ad2a3efb4b5bd8fb454568919d114","size":3233},
{"path": "truco/src/views/layer/", "name": "TrucoDialogBase.lua", "md5": "e2cb88247dcb96df26337c7884d020cf","size":2306},
{"path": "truco/src/views/layer/", "name": "TrucoHelpLayer.lua", "md5": "38362cde2fe8d26c63b799d64a77441f","size":1187},
{"path": "truco/src/views/layer/", "name": "TrucoHuDongLayer.lua", "md5": "30838819b886511e1298ed72a0e12b5d","size":4893},
{"path": "truco/src/views/layer/", "name": "TrucoPlayerLayer.lua", "md5": "6d6ee64cbe3f28e93841f88d32a0dffb","size":12553},
{"path": "truco/src/views/layer/", "name": "TrucoPlayerNode.lua", "md5": "8ace61ec36e2f3996683b8febfa03b70","size":11129},
{"path": "truco/src/views/layer/", "name": "TrucoResultNode.lua", "md5": "5dc7d7807e516ec9738a4f465f475d70","size":10357},
{"path": "truco/src/views/layer/", "name": "TrucoScoreNode.lua", "md5": "763854a623e509ea8987de766f3df4da","size":10766},
{"path": "truco/src/views/layer/", "name": "TrucoStartAniNode.lua", "md5": "d63640cba961f6520ab9a8fa62a2a6f5","size":2532},
{"path": "truco/src/views/layer/", "name": "TrucoTrusteeNode.lua", "md5": "d769ff505deccb5a400b55227b5e7d35","size":1933},
{"path": "truco/src/views/layer/", "name": "TrucoViewLayer.lua", "md5": "97790ca4c07617ff8d54c8d3eb44b076","size":36688},
{"path": "truco/src/views/layer/", "name": "TrucoWaterMaskNode.lua", "md5": "2f88a52faa3fd48fbb2268e41e1534cd","size":2285}
,{"allcount":455}]}