{
"skeleton": { "hash": "50u0EAgllfWCIrcSEl3j54bJWJo", "spine": "3.6.34", "width": 0, "height": 0, "images": "./images/" },
"bones": [
	{ "name": "root" },
	{ "name": "bone2", "parent": "root", "x": 32.33, "y": -100.06 },
	{ "name": "bone6", "parent": "bone2", "x": -19.91, "y": 87.86 },
	{ "name": "dfjhfjj", "parent": "bone2", "x": 772.97, "y": 115.04 },
	{ "name": "guangdian", "parent": "bone6", "x": -40.42, "y": 16.47 },
	{ "name": "guangdian2", "parent": "bone6", "rotation": -53.17, "x": 63.53, "y": -17.03, "scaleX": 0.493, "scaleY": 0.493 },
	{ "name": "guangdian3", "parent": "bone6", "rotation": -129.28, "x": 27.72, "y": 10.31, "scaleX": 1.208, "scaleY": 1.208 },
	{ "name": "xingxing", "parent": "bone6", "x": 64.26, "y": 28.71, "scaleX": 0.519, "scaleY": 0.519 },
	{ "name": "xingxing2", "parent": "bone6", "rotation": 44.09, "x": 11.13, "y": -25.19 }
],
"slots": [
	{ "name": "xingxing", "bone": "xingxing", "attachment": "xingxing", "blend": "additive" },
	{ "name": "xingxing2", "bone": "xingxing2", "attachment": "xingxing", "blend": "additive" },
	{ "name": "guangdian", "bone": "guangdian", "attachment": "guangdian", "blend": "additive" },
	{ "name": "guangdian2", "bone": "guangdian2", "attachment": "guangdian", "blend": "additive" },
	{ "name": "guangdian3", "bone": "guangdian3", "attachment": "guangdian", "blend": "additive" },
	{ "name": "dfjhfjj", "bone": "dfjhfjj", "blend": "additive" }
],
"skins": {
	"default": {
		"dfjhfjj": {
			"caishan": { "scaleX": 2, "scaleY": 2, "width": 214, "height": 212 }
		},
		"guangdian": {
			"guangdian": { "x": -0.09, "y": 0.12, "width": 30, "height": 30 }
		},
		"guangdian2": {
			"guangdian": { "x": -0.09, "y": 0.12, "width": 30, "height": 30 }
		},
		"guangdian3": {
			"guangdian": { "x": -0.09, "y": 0.12, "width": 30, "height": 30 }
		},
		"xingxing": {
			"xingxing": { "x": -0.55, "y": -0.39, "width": 74, "height": 74 }
		},
		"xingxing2": {
			"xingxing": { "x": -0.55, "y": -0.39, "width": 74, "height": 74 }
		}
	}
},
"animations": {
	"daiji": {
		"slots": {
			"dfjhfjj": {
				"color": [
					{ "time": 0, "color": "ffffff00" },
					{ "time": 0.1667, "color": "ffffffa6" },
					{ "time": 0.4333, "color": "ffffff32" },
					{ "time": 1, "color": "ffffff00", "curve": "stepped" },
					{ "time": 2, "color": "ffffff00" },
					{ "time": 2.1667, "color": "ffffffa6" },
					{ "time": 2.4333, "color": "ffffff32" },
					{ "time": 3, "color": "ffffff00" }
				],
				"attachment": [
					{ "time": 0, "name": "caishan" }
				]
			},
			"guangdian": {
				"color": [
					{ "time": 0, "color": "ffffff00" },
					{
						"time": 0.1667,
						"color": "ffffffff",
						"curve": [ 0.25, 0, 1, 1 ]
					},
					{ "time": 0.8333, "color": "ffffff00", "curve": "stepped" },
					{ "time": 0.9333, "color": "ffffff00" },
					{
						"time": 1.1,
						"color": "ffffffff",
						"curve": [ 0.25, 0, 1, 1 ]
					},
					{ "time": 1.7667, "color": "ffffff00", "curve": "stepped" },
					{ "time": 1.9, "color": "ffffff00" },
					{
						"time": 2.0667,
						"color": "ffffffff",
						"curve": [ 0.25, 0, 1, 1 ]
					},
					{ "time": 2.7333, "color": "ffffff00", "curve": "stepped" },
					{ "time": 2.8667, "color": "ffffff00" },
					{
						"time": 3.0333,
						"color": "ffffffff",
						"curve": [ 0.25, 0, 1, 1 ]
					},
					{ "time": 3.7, "color": "ffffff00", "curve": "stepped" },
					{ "time": 3.8333, "color": "ffffff00" }
				],
				"attachment": [
					{ "time": 0, "name": "guangdian" },
					{ "time": 0.9333, "name": "guangdian" },
					{ "time": 1.9, "name": "guangdian" },
					{ "time": 2.8667, "name": "guangdian" },
					{ "time": 3.8333, "name": "guangdian" }
				]
			},
			"guangdian2": {
				"color": [
					{
						"time": 0,
						"color": "ffffff5f",
						"curve": [ 0.6, 0.58, 1, 1 ]
					},
					{ "time": 0.2, "color": "ffffff00", "curve": "stepped" },
					{ "time": 0.3333, "color": "ffffff00" },
					{
						"time": 0.5,
						"color": "ffffffff",
						"curve": [ 0.25, 0, 1, 1 ]
					},
					{ "time": 1.1667, "color": "ffffff00", "curve": "stepped" },
					{ "time": 1.2667, "color": "ffffff00" },
					{
						"time": 1.4333,
						"color": "ffffffff",
						"curve": [ 0.25, 0, 1, 1 ]
					},
					{ "time": 2.1, "color": "ffffff00", "curve": "stepped" },
					{ "time": 2.2333, "color": "ffffff00" },
					{
						"time": 2.4,
						"color": "ffffffff",
						"curve": [ 0.25, 0, 1, 1 ]
					},
					{ "time": 3.0667, "color": "ffffff00", "curve": "stepped" },
					{ "time": 3.2, "color": "ffffff00" },
					{
						"time": 3.3667,
						"color": "ffffffff",
						"curve": [ 0.211, 0, 0.716, 0.63 ]
					},
					{ "time": 3.8333, "color": "ffffff5f" }
				],
				"attachment": [
					{ "time": 0, "name": "guangdian" },
					{ "time": 0.9333, "name": "guangdian" },
					{ "time": 1.9, "name": "guangdian" },
					{ "time": 2.8667, "name": "guangdian" },
					{ "time": 3.8333, "name": "guangdian" }
				]
			},
			"guangdian3": {
				"color": [
					{
						"time": 0,
						"color": "ffffffe4",
						"curve": [ 0.4, 0.29, 1, 1 ]
					},
					{ "time": 0.5333, "color": "ffffff00", "curve": "stepped" },
					{ "time": 0.6667, "color": "ffffff00" },
					{
						"time": 0.8333,
						"color": "ffffffff",
						"curve": [ 0.25, 0, 1, 1 ]
					},
					{ "time": 1.5, "color": "ffffff00", "curve": "stepped" },
					{ "time": 1.6, "color": "ffffff00" },
					{
						"time": 1.7667,
						"color": "ffffffff",
						"curve": [ 0.25, 0, 1, 1 ]
					},
					{ "time": 2.4333, "color": "ffffff00", "curve": "stepped" },
					{ "time": 2.5667, "color": "ffffff00" },
					{
						"time": 2.7333,
						"color": "ffffffff",
						"curve": [ 0.25, 0, 1, 1 ]
					},
					{ "time": 3.4, "color": "ffffff00", "curve": "stepped" },
					{ "time": 3.5333, "color": "ffffff00" },
					{
						"time": 3.7,
						"color": "ffffffff",
						"curve": [ 0.25, 0, 0.6, 0.38 ]
					},
					{ "time": 3.8333, "color": "ffffffe4" }
				],
				"attachment": [
					{ "time": 0, "name": "guangdian" },
					{ "time": 0.9333, "name": "guangdian" },
					{ "time": 1.9, "name": "guangdian" },
					{ "time": 2.8667, "name": "guangdian" },
					{ "time": 3.8333, "name": "guangdian" }
				]
			},
			"xingxing": {
				"color": [
					{
						"time": 0,
						"color": "ffffff5f",
						"curve": [ 0.6, 0.58, 1, 1 ]
					},
					{ "time": 0.2, "color": "ffffff00", "curve": "stepped" },
					{ "time": 0.3333, "color": "ffffff00" },
					{
						"time": 0.5,
						"color": "ffffffff",
						"curve": [ 0.25, 0, 1, 1 ]
					},
					{ "time": 1.1667, "color": "ffffff00", "curve": "stepped" },
					{ "time": 1.2667, "color": "ffffff00" },
					{
						"time": 1.4333,
						"color": "ffffffff",
						"curve": [ 0.25, 0, 1, 1 ]
					},
					{ "time": 2.1, "color": "ffffff00", "curve": "stepped" },
					{ "time": 2.2333, "color": "ffffff00" },
					{
						"time": 2.4,
						"color": "ffffffff",
						"curve": [ 0.25, 0, 1, 1 ]
					},
					{ "time": 3.0667, "color": "ffffff00", "curve": "stepped" },
					{ "time": 3.2, "color": "ffffff00" },
					{
						"time": 3.3667,
						"color": "ffffffff",
						"curve": [ 0.211, 0, 0.716, 0.63 ]
					},
					{ "time": 3.8333, "color": "ffffff5f" }
				],
				"attachment": [
					{ "time": 0, "name": "xingxing" },
					{ "time": 0.9333, "name": "xingxing" },
					{ "time": 1.9, "name": "xingxing" },
					{ "time": 2.8667, "name": "xingxing" },
					{ "time": 3.8333, "name": "xingxing" }
				]
			},
			"xingxing2": {
				"color": [
					{ "time": 0, "color": "ffffffcc" },
					{
						"time": 0.0333,
						"color": "ffffffff",
						"curve": [ 0.25, 0, 1, 1 ]
					},
					{ "time": 0.7, "color": "ffffff00", "curve": "stepped" },
					{ "time": 0.8333, "color": "ffffff00" },
					{
						"time": 1,
						"color": "ffffffff",
						"curve": [ 0.25, 0, 1, 1 ]
					},
					{ "time": 1.6667, "color": "ffffff00", "curve": "stepped" },
					{ "time": 1.7667, "color": "ffffff00" },
					{
						"time": 1.9333,
						"color": "ffffffff",
						"curve": [ 0.25, 0, 1, 1 ]
					},
					{ "time": 2.6, "color": "ffffff00", "curve": "stepped" },
					{ "time": 2.7333, "color": "ffffff00" },
					{
						"time": 2.9,
						"color": "ffffffff",
						"curve": [ 0.25, 0, 1, 1 ]
					},
					{ "time": 3.5667, "color": "ffffff00", "curve": "stepped" },
					{ "time": 3.7, "color": "ffffff00" },
					{ "time": 3.8333, "color": "ffffffcc" }
				],
				"attachment": [
					{ "time": 0, "name": "xingxing" },
					{ "time": 0.9333, "name": "xingxing" },
					{ "time": 1.9, "name": "xingxing" },
					{ "time": 2.8667, "name": "xingxing" },
					{ "time": 3.8333, "name": "xingxing" }
				]
			}
		},
		"bones": {
			"guangdian": {
				"rotate": [
					{ "time": 0, "angle": 0, "curve": "stepped" },
					{ "time": 0.9333, "angle": -56.79, "curve": "stepped" },
					{ "time": 1.9, "angle": 56.75, "curve": "stepped" },
					{ "time": 2.8667, "angle": 0, "curve": "stepped" },
					{ "time": 3.8333, "angle": 0 }
				],
				"translate": [
					{ "time": 0, "x": 0, "y": 0, "curve": "stepped" },
					{ "time": 0.9333, "x": 15.37, "y": 15.7, "curve": "stepped" },
					{ "time": 1.9, "x": 0, "y": 0, "curve": "stepped" },
					{ "time": 2.8667, "x": 51.34, "y": 3.6, "curve": "stepped" },
					{ "time": 3.8333, "x": 0, "y": 0 }
				],
				"scale": [
					{ "time": 0, "x": 0.159, "y": 0.159 },
					{
						"time": 0.1667,
						"x": 1,
						"y": 1,
						"curve": [ 0.25, 0, 1, 1 ]
					},
					{ "time": 0.8333, "x": 0.576, "y": 0.576, "curve": "stepped" },
					{ "time": 0.9333, "x": 0.159, "y": 0.159 },
					{
						"time": 1.1,
						"x": 1,
						"y": 1,
						"curve": [ 0.25, 0, 1, 1 ]
					},
					{ "time": 1.7667, "x": 0.576, "y": 0.576, "curve": "stepped" },
					{ "time": 1.9, "x": 0.159, "y": 0.159 },
					{
						"time": 2.0667,
						"x": 1,
						"y": 1,
						"curve": [ 0.25, 0, 1, 1 ]
					},
					{ "time": 2.7333, "x": 0.576, "y": 0.576, "curve": "stepped" },
					{ "time": 2.8667, "x": 0.159, "y": 0.159 },
					{
						"time": 3.0333,
						"x": 1,
						"y": 1,
						"curve": [ 0.25, 0, 1, 1 ]
					},
					{ "time": 3.7, "x": 0.576, "y": 0.576, "curve": "stepped" },
					{ "time": 3.8333, "x": 0.159, "y": 0.159 }
				]
			},
			"guangdian2": {
				"rotate": [
					{ "time": 0, "angle": -66.65, "curve": "stepped" },
					{ "time": 0.3333, "angle": 0, "curve": "stepped" },
					{ "time": 1.2667, "angle": 74.85, "curve": "stepped" },
					{ "time": 2.2333, "angle": 54.56, "curve": "stepped" },
					{ "time": 3.2, "angle": -66.65, "curve": "stepped" },
					{ "time": 3.8333, "angle": -66.65 }
				],
				"translate": [
					{ "time": 0, "x": -16.35, "y": 32.37, "curve": "stepped" },
					{ "time": 0.3333, "x": 0, "y": 0, "curve": "stepped" },
					{ "time": 1.2667, "x": -83.71, "y": 2.94, "curve": "stepped" },
					{ "time": 2.2333, "x": 10.79, "y": 12.75, "curve": "stepped" },
					{ "time": 3.2, "x": -16.35, "y": 32.37, "curve": "stepped" },
					{ "time": 3.8333, "x": -16.35, "y": 32.37 }
				],
				"scale": [
					{
						"time": 0,
						"x": 0.734,
						"y": 0.734,
						"curve": [ 0.6, 0.58, 1, 1 ]
					},
					{ "time": 0.2, "x": 0.574, "y": 0.574, "curve": "stepped" },
					{ "time": 0.3333, "x": 0.163, "y": 0.163 },
					{
						"time": 0.5,
						"x": 1,
						"y": 1,
						"curve": [ 0.25, 0, 1, 1 ]
					},
					{ "time": 1.1667, "x": 0.574, "y": 0.574, "curve": "stepped" },
					{ "time": 1.2667, "x": 0.163, "y": 0.163 },
					{
						"time": 1.4333,
						"x": 1,
						"y": 1,
						"curve": [ 0.25, 0, 1, 1 ]
					},
					{ "time": 2.1, "x": 0.574, "y": 0.574, "curve": "stepped" },
					{ "time": 2.2333, "x": 0.163, "y": 0.163 },
					{
						"time": 2.4,
						"x": 1,
						"y": 1,
						"curve": [ 0.25, 0, 1, 1 ]
					},
					{ "time": 3.0667, "x": 0.574, "y": 0.574, "curve": "stepped" },
					{ "time": 3.2, "x": 0.163, "y": 0.163 },
					{
						"time": 3.3667,
						"x": 1,
						"y": 1,
						"curve": [ 0.211, 0, 0.716, 0.63 ]
					},
					{ "time": 3.8333, "x": 0.734, "y": 0.734 }
				]
			},
			"xingxing": {
				"rotate": [
					{ "time": 0, "angle": 96.12, "curve": "stepped" },
					{ "time": 0.3333, "angle": 0, "curve": "stepped" },
					{ "time": 1.2667, "angle": -50.4, "curve": "stepped" },
					{ "time": 2.2333, "angle": -40.85, "curve": "stepped" },
					{ "time": 3.2, "angle": 96.12, "curve": "stepped" },
					{ "time": 3.8333, "angle": 96.12 }
				],
				"translate": [
					{ "time": 0, "x": 2.94, "y": -38.91, "curve": "stepped" },
					{ "time": 0.3333, "x": 0, "y": 0, "curve": "stepped" },
					{ "time": 1.2667, "x": 2.29, "y": -17, "curve": "stepped" },
					{ "time": 2.2333, "x": -11.45, "y": -15.04, "curve": "stepped" },
					{ "time": 3.2, "x": 2.94, "y": -38.91, "curve": "stepped" },
					{ "time": 3.8333, "x": 2.94, "y": -38.91 }
				],
				"scale": [
					{
						"time": 0,
						"x": 0.735,
						"y": 0.735,
						"curve": [ 0.6, 0.58, 1, 1 ]
					},
					{ "time": 0.2, "x": 0.576, "y": 0.576, "curve": "stepped" },
					{ "time": 0.3333, "x": 0.159, "y": 0.159 },
					{
						"time": 0.5,
						"x": 1,
						"y": 1,
						"curve": [ 0.25, 0, 1, 1 ]
					},
					{ "time": 1.1667, "x": 0.576, "y": 0.576, "curve": "stepped" },
					{ "time": 1.2667, "x": 0.159, "y": 0.159 },
					{
						"time": 1.4333,
						"x": 1,
						"y": 1,
						"curve": [ 0.25, 0, 1, 1 ]
					},
					{ "time": 2.1, "x": 0.576, "y": 0.576, "curve": "stepped" },
					{ "time": 2.2333, "x": 0.159, "y": 0.159 },
					{
						"time": 2.4,
						"x": 1,
						"y": 1,
						"curve": [ 0.25, 0, 1, 1 ]
					},
					{ "time": 3.0667, "x": 0.576, "y": 0.576, "curve": "stepped" },
					{ "time": 3.2, "x": 0.159, "y": 0.159 },
					{
						"time": 3.3667,
						"x": 1,
						"y": 1,
						"curve": [ 0.211, 0, 0.716, 0.63 ]
					},
					{ "time": 3.8333, "x": 0.735, "y": 0.735 }
				]
			},
			"guangdian3": {
				"rotate": [
					{ "time": 0, "angle": 57.08, "curve": "stepped" },
					{ "time": 0.6667, "angle": 0, "curve": "stepped" },
					{ "time": 1.6, "angle": 60.51, "curve": "stepped" },
					{ "time": 2.5667, "angle": -28.28, "curve": "stepped" },
					{ "time": 3.5333, "angle": 57.08, "curve": "stepped" },
					{ "time": 3.8333, "angle": 57.08 }
				],
				"translate": [
					{ "time": 0, "x": -49.05, "y": -12.75, "curve": "stepped" },
					{ "time": 0.6667, "x": 0, "y": 0, "curve": "stepped" },
					{ "time": 1.6, "x": -3.92, "y": -32.05, "curve": "stepped" },
					{ "time": 2.5667, "x": -0.33, "y": 22.89, "curve": "stepped" },
					{ "time": 3.5333, "x": -49.05, "y": -12.75, "curve": "stepped" },
					{ "time": 3.8333, "x": -49.05, "y": -12.75 }
				],
				"scale": [
					{
						"time": 0,
						"x": 0.956,
						"y": 0.956,
						"curve": [ 0.4, 0.29, 1, 1 ]
					},
					{ "time": 0.5333, "x": 0.574, "y": 0.574, "curve": "stepped" },
					{ "time": 0.6667, "x": 0.163, "y": 0.163 },
					{
						"time": 0.8333,
						"x": 1,
						"y": 1,
						"curve": [ 0.25, 0, 1, 1 ]
					},
					{ "time": 1.5, "x": 0.574, "y": 0.574, "curve": "stepped" },
					{ "time": 1.6, "x": 0.163, "y": 0.163 },
					{
						"time": 1.7667,
						"x": 1,
						"y": 1,
						"curve": [ 0.25, 0, 1, 1 ]
					},
					{ "time": 2.4333, "x": 0.574, "y": 0.574, "curve": "stepped" },
					{ "time": 2.5667, "x": 0.163, "y": 0.163 },
					{
						"time": 2.7333,
						"x": 1,
						"y": 1,
						"curve": [ 0.25, 0, 1, 1 ]
					},
					{ "time": 3.4, "x": 0.574, "y": 0.574, "curve": "stepped" },
					{ "time": 3.5333, "x": 0.163, "y": 0.163 },
					{
						"time": 3.7,
						"x": 1,
						"y": 1,
						"curve": [ 0.25, 0, 0.6, 0.38 ]
					},
					{ "time": 3.8333, "x": 0.956, "y": 0.956 }
				]
			},
			"xingxing2": {
				"rotate": [
					{ "time": 0, "angle": -0.03, "curve": "stepped" },
					{ "time": 0.8333, "angle": 0, "curve": "stepped" },
					{ "time": 1.7667, "angle": -58.48, "curve": "stepped" },
					{ "time": 2.7333, "angle": -59.69, "curve": "stepped" },
					{ "time": 3.7, "angle": -0.03, "curve": "stepped" },
					{ "time": 3.8333, "angle": -0.03 }
				],
				"translate": [
					{ "time": 0, "x": 25.51, "y": 12.1, "curve": "stepped" },
					{ "time": 0.8333, "x": 0, "y": 0, "curve": "stepped" },
					{ "time": 1.7667, "x": 48.07, "y": 11.12, "curve": "stepped" },
					{ "time": 2.7333, "x": 8.5, "y": 1.96, "curve": "stepped" },
					{ "time": 3.7, "x": 25.51, "y": 12.1, "curve": "stepped" },
					{ "time": 3.8333, "x": 25.51, "y": 12.1 }
				],
				"scale": [
					{ "time": 0, "x": 0.832, "y": 0.832 },
					{
						"time": 0.0333,
						"x": 1,
						"y": 1,
						"curve": [ 0.25, 0, 1, 1 ]
					},
					{ "time": 0.7, "x": 0.576, "y": 0.576, "curve": "stepped" },
					{ "time": 0.8333, "x": 0.159, "y": 0.159 },
					{
						"time": 1,
						"x": 1,
						"y": 1,
						"curve": [ 0.25, 0, 1, 1 ]
					},
					{ "time": 1.6667, "x": 0.576, "y": 0.576, "curve": "stepped" },
					{ "time": 1.7667, "x": 0.159, "y": 0.159 },
					{
						"time": 1.9333,
						"x": 1,
						"y": 1,
						"curve": [ 0.25, 0, 1, 1 ]
					},
					{ "time": 2.6, "x": 0.576, "y": 0.576, "curve": "stepped" },
					{ "time": 2.7333, "x": 0.159, "y": 0.159 },
					{
						"time": 2.9,
						"x": 1,
						"y": 1,
						"curve": [ 0.25, 0, 1, 1 ]
					},
					{ "time": 3.5667, "x": 0.576, "y": 0.576, "curve": "stepped" },
					{ "time": 3.7, "x": 0.159, "y": 0.159 },
					{ "time": 3.8333, "x": 0.832, "y": 0.832 }
				]
			},
			"dfjhfjj": {
				"translate": [
					{ "time": 0, "x": -774.28, "y": -11.59, "curve": "stepped" },
					{ "time": 2, "x": -774.28, "y": -11.59 }
				],
				"scale": [
					{ "time": 0, "x": 0.205, "y": 0.205 },
					{ "time": 1, "x": 0.528, "y": 0.528, "curve": "stepped" },
					{ "time": 2, "x": 0.205, "y": 0.205 },
					{ "time": 3, "x": 0.528, "y": 0.528 }
				]
			},
			"bone2": {
				"translate": [
					{ "time": 0, "x": -31.75, "y": -1.13 }
				]
			}
		}
	}
}
}